{
 "ValuelessSupport": {
  "status": "Graduated",
  "detector": "ValuelessSupportPlay",
  "match": "ValuelessSupportPlay",
  "fix": "前提条件Gate(evolve_supporters+_has_evolution_target)",
  "first_seen": "2026-07-03",
  "graduated": "2026-07-03",
  "cycles": [
   15,
   0,
   0
  ],
  "regressions": 0,
  "cause": "Playability Gate欠如(前提条件の未確認)"
 },
 "LillieLastStand": {
  "status": "Graduated",
  "detector": "LastStand(リーリエ打てたのに未使用)",
  "match": "LastStand|単騎×被KO×非致死|リーリエ打てたのに未使用",
  "fix": "Lillie緊急Gate(単騎×被KO圏×手札にたね/ポフィン無し)",
  "first_seen": "2026-07-03",
  "graduated": "2026-07-03",
  "cycles": [
   11,
   0,
   0
  ],
  "regressions": 0,
  "cause": "緊急時Gate欠如"
 },
 "WallRetreat": {
  "status": "Graduated",
  "detector": "WallRetreat",
  "match": "WallRetreat",
  "fix": "後段_should_repositionに先攻T1ガード",
  "first_seen": "2026-07-03",
  "graduated": "2026-07-03",
  "cycles": [
   2,
   0,
   0
  ],
  "regressions": 0,
  "cause": "Playability Gate欠如(前提条件の未確認)"
 },
 "MissedLethal(Boss順序)": {
  "status": "Graduated",
  "detector": "MissedLethal",
  "match": "MissedLethal",
  "fix": "assume_hand_attach(ボスゲート/ガスト選択を手貼り後火力で評価)+検出器のイグニ3エネ換算修正",
  "first_seen": "2026-07-03",
  "graduated": "2026-07-03",
  "cycles": [
   1,
   1,
   0,
   0
  ],
  "regressions": 0,
  "cause": "評価タイミング(順序: 手貼り前に判断)"
 },
 "DeadMoveAttack": {
  "status": "Graduated",
  "detector": "DeadMoveAttack",
  "match": "DeadMoveAttack",
  "fix": "interpret_move partner解釈+_dead_by_partner(相方不在の技=0評価/全滅ならEND)+play_priority相方+15",
  "first_seen": "2026-07-03",
  "graduated": "2026-07-03",
  "cycles": [
   16,
   0,
   0
  ],
  "regressions": 0,
  "cause": "Playability Gate欠如(前提条件の未確認)"
 },
 "SpreadSkew": {
  "status": "Graduated",
  "detector": "SpreadSkew",
  "match": "SpreadSkew",
  "fix": "_spread_keyにsnipe項(主力線たね×撒き2発圏をreduceより優先)",
  "first_seen": "2026-07-03",
  "graduated": "2026-07-03",
  "cycles": [
   19,
   0,
   0
  ],
  "regressions": 0,
  "cause": "優先度序列の設計(将来脅威の評価)"
 },
 "FetchSkew": {
  "status": "Open",
  "detector": "FetchSkew",
  "match": "FetchSkew",
  "observational": true,
  "first_seen": "2026-07-03",
  "cycles": [
   111
  ],
  "regressions": 0,
  "note": "観測カウンタ(トウコのエネ選択を○×問わず全記録)=違反件数でない。Fetch Future Value(凍結中)の素材",
  "cause": "Fetch Future Value(観測素材・凍結中)"
 },
 "LastStand": {
  "status": "Open",
  "detector": "LastStand",
  "match": "LastStand",
  "first_seen": "2026-07-03",
  "cycles": [
   19
  ],
  "regressions": 0,
  "cause": "大半がH2:選択肢なし(リーリエ無し=bot裁量外)",
  "ev": {
   "cost": "大",
   "gain": "小"
  }
 },
 "UnusedSupporterRight": {
  "status": "Open",
  "detector": "UnusedSupporterRight",
  "match": "UnusedSupporterRight",
  "first_seen": "2026-07-03",
  "cycles": [
   33
  ],
  "regressions": 0,
  "cause": "Support Value(サポ権の価値比較)・大半は相手bot側",
  "ev": {
   "cost": "中(A/B/C/D分類が先)",
   "gain": "要分類(過去ExplainでB=価値比較ミスは1件のみ=大半H1温存の可能性)"
  }
 },
 "WastedInvestment": {
  "status": "Open",
  "detector": "WastedInvestment",
  "match": "WastedInvestment",
  "first_seen": "2026-07-03",
  "cycles": [
   22
  ],
  "regressions": 0,
  "cause": "Attach Future Value欠如(Episode5凍結中)",
  "ev": {
   "cost": "大",
   "gain": "小-中(v7分析で84%は正当なunlock投資)"
  }
 }
}